jejunuMeals/__init__.py
jejunuMeals-1.4.dist-info/METADATA
jejunuMeals-1.4.dist-info/RECORD
jejunuMeals-1.4.dist-info/WHEEL
jejunuMeals-1.4.dist-info/top_level.txt
