Metadata-Version: 2.1
Name: jejunuMeals
Version: 1.4
Summary: Jeju National University meal data crawler
Home-page: https://github.com/BetaF1sh/jejunuMeals
Author: BetaF1sh
Author-email: iam@muhun.kim
License: MIT
Platform: UNKNOWN
Classifier: Programming Language :: Python
Classifier: Programming Language :: Python :: 3.5
Classifier: Programming Language :: Python :: 3.6
Classifier: Programming Language :: Python :: 3.7
Classifier: Programming Language :: Python :: 3 :: Only
Classifier: License :: OSI Approved :: MIT License
Requires-Python: >=3
Requires-Dist: bs4
Requires-Dist: requests
